aix360/__init__.py
aix360/algorithms/__init__.py
aix360/algorithms/die.py
aix360/algorithms/dise.py
aix360/algorithms/gbbe.py
aix360/algorithms/gwbe.py
aix360/algorithms/lbbe.py
aix360/algorithms/lwbe.py
aix360/algorithms/tslbbe.py
aix360/algorithms/cofrnet/CoFrNet.py
aix360/algorithms/cofrnet/CustomizedLinearClasses.py
aix360/algorithms/cofrnet/__init__.py
aix360/algorithms/cofrnet/utils.py
aix360/algorithms/contrastive/CEM.py
aix360/algorithms/contrastive/CEM_MAF.py
aix360/algorithms/contrastive/CEM_MAF_aen_PN.py
aix360/algorithms/contrastive/CEM_MAF_aen_PP.py
aix360/algorithms/contrastive/CEM_MAF_utils.py
aix360/algorithms/contrastive/CEM_aen.py
aix360/algorithms/contrastive/__init__.py
aix360/algorithms/contrastive/classifiers.py
aix360/algorithms/contrastive/dwnld_CEM_MAF_celebA.py
aix360/algorithms/dipvae/__init__.py
aix360/algorithms/dipvae/dipvae.py
aix360/algorithms/dipvae/dipvae_utils.py
aix360/algorithms/gce/__init__.py
aix360/algorithms/gce/gce.py
aix360/algorithms/imd/__init__.py
aix360/algorithms/imd/imd.py
aix360/algorithms/imd/jst.py
aix360/algorithms/imd/rule.py
aix360/algorithms/imd/utils.py
aix360/algorithms/lime/__init__.py
aix360/algorithms/lime/lime_wrapper.py
aix360/algorithms/matching/__init__.py
aix360/algorithms/matching/order_constraints.py
aix360/algorithms/nncontrastive/__init__.py
aix360/algorithms/nncontrastive/embedding.py
aix360/algorithms/nncontrastive/nncontrastive.py
aix360/algorithms/nncontrastive/utils.py
aix360/algorithms/profwt/__init__.py
aix360/algorithms/profwt/attach_probe_checkpoint.py
aix360/algorithms/profwt/profwt.py
aix360/algorithms/profwt/resnet_keras_model.py
aix360/algorithms/profwt/sample_weight_from_probes.py
aix360/algorithms/profwt/train_probes.py
aix360/algorithms/protodash/PDASH.py
aix360/algorithms/protodash/PDASH_utils.py
aix360/algorithms/protodash/__init__.py
aix360/algorithms/rbm/BRCG.py
aix360/algorithms/rbm/GLRM.py
aix360/algorithms/rbm/__init__.py
aix360/algorithms/rbm/beam_search.py
aix360-0.3.0.dist-info/LICENSE
aix360-0.3.0.dist-info/METADATA
aix360-0.3.0.dist-info/WHEEL
aix360-0.3.0.dist-info/top_level.txt
aix360-0.3.0.dist-info/RECORD
