Metadata-Version: 2.1
Name: aix360
Version: 0.3.0
Summary: AI Explainability 360 v0.3.0
Author-email: aix360 developers <aix360@us.ibm.com>
Project-URL: Homepage, https://github.com/Trusted-AI/AIX360
Project-URL: Bug Tracker, https://github.com/Trusted-AI/AIX360/issues
Classifier: Programming Language :: Python :: 3
Classifier: License :: OSI Approved :: Apache Software License
Classifier: Operating System :: OS Independent
Requires-Python: >=3.6
License-File: LICENSE
Requires-Dist: numpy
Requires-Dist: pandas
Requires-Dist: scikit-learn
Requires-Dist: matplotlib
Provides-Extra: cofrnet
Requires-Dist: pandas (<2.0.0) ; extra == 'cofrnet'
Requires-Dist: torch ; extra == 'cofrnet'
Requires-Dist: tqdm ; extra == 'cofrnet'
Provides-Extra: contrastive
Requires-Dist: keras (==2.3.1) ; extra == 'contrastive'
Requires-Dist: tensorflow (==1.14) ; extra == 'contrastive'
Requires-Dist: requests ; extra == 'contrastive'
Requires-Dist: scipy (>=0.17) ; extra == 'contrastive'
Requires-Dist: scikit-image ; extra == 'contrastive'
Requires-Dist: torch ; extra == 'contrastive'
Requires-Dist: h5py (<3.0.0) ; extra == 'contrastive'
Provides-Extra: default
Requires-Dist: numpy ; extra == 'default'
Requires-Dist: pandas ; extra == 'default'
Requires-Dist: scikit-learn ; extra == 'default'
Requires-Dist: matplotlib ; extra == 'default'
Provides-Extra: dipvae
Requires-Dist: matplotlib ; extra == 'dipvae'
Requires-Dist: torch ; extra == 'dipvae'
Requires-Dist: torchvision ; extra == 'dipvae'
Provides-Extra: gce
Requires-Dist: pandas (<2.0.0) ; extra == 'gce'
Requires-Dist: shap ; extra == 'gce'
Requires-Dist: numba (<=0.56) ; extra == 'gce'
Requires-Dist: requests ; extra == 'gce'
Provides-Extra: imd
Requires-Dist: numpy ; extra == 'imd'
Requires-Dist: pandas ; extra == 'imd'
Requires-Dist: scikit-learn ; extra == 'imd'
Requires-Dist: matplotlib ; extra == 'imd'
Requires-Dist: networkx ; extra == 'imd'
Requires-Dist: graphviz ; extra == 'imd'
Requires-Dist: pygraphviz ; extra == 'imd'
Provides-Extra: lime
Requires-Dist: lime ; extra == 'lime'
Requires-Dist: tqdm ; extra == 'lime'
Requires-Dist: pandas ; extra == 'lime'
Provides-Extra: nncontrastive
Requires-Dist: pandas (<2.0.0) ; extra == 'nncontrastive'
Requires-Dist: tensorflow (==2.9.3) ; extra == 'nncontrastive'
Provides-Extra: profwt
Requires-Dist: keras (==2.3.1) ; extra == 'profwt'
Requires-Dist: scipy (>=0.17) ; extra == 'profwt'
Requires-Dist: tensorflow (==1.14) ; extra == 'profwt'
Provides-Extra: protodash
Requires-Dist: scikit-learn ; extra == 'protodash'
Requires-Dist: xport ; extra == 'protodash'
Requires-Dist: scipy (<=1.10.1,>=0.17) ; extra == 'protodash'
Requires-Dist: cvxpy ; extra == 'protodash'
Requires-Dist: requests ; extra == 'protodash'
Provides-Extra: rbm
Requires-Dist: matplotlib ; extra == 'rbm'
Requires-Dist: pandas (<2.0.0) ; extra == 'rbm'
Requires-Dist: scipy (<=1.10.1,>=0.17) ; extra == 'rbm'
Requires-Dist: scikit-learn (<1.2.0) ; extra == 'rbm'
Requires-Dist: cvxpy (>=1.1) ; extra == 'rbm'
Requires-Dist: numpy (<=1.24.3) ; extra == 'rbm'
Provides-Extra: rule_induction
Requires-Dist: matplotlib ; extra == 'rule_induction'
Requires-Dist: numba ; extra == 'rule_induction'
Requires-Dist: pandas (<2.0.0) ; extra == 'rule_induction'
Requires-Dist: scikit-learn ; extra == 'rule_induction'
Requires-Dist: nyoka ; extra == 'rule_induction'
Requires-Dist: cvxpy ; extra == 'rule_induction'
Requires-Dist: xmltodict (==0.12.0) ; extra == 'rule_induction'
Provides-Extra: shap
Requires-Dist: keras (==2.3.1) ; extra == 'shap'
Requires-Dist: tensorflow (==1.14) ; extra == 'shap'
Requires-Dist: matplotlib ; extra == 'shap'
Requires-Dist: numba ; extra == 'shap'
Requires-Dist: pandas (<2.0.0) ; extra == 'shap'
Requires-Dist: shap ; extra == 'shap'
Requires-Dist: tqdm ; extra == 'shap'
Provides-Extra: ted
Requires-Dist: pandas ; extra == 'ted'
Requires-Dist: scikit-learn ; extra == 'ted'
Provides-Extra: tsice
Requires-Dist: pandas (<2.0.0) ; extra == 'tsice'
Requires-Dist: scipy ; extra == 'tsice'
Requires-Dist: plotly ; extra == 'tsice'
Requires-Dist: ipython ; extra == 'tsice'
Requires-Dist: kaleido ; extra == 'tsice'
Requires-Dist: requests ; extra == 'tsice'
Provides-Extra: tslime
Requires-Dist: pandas (<2.0.0) ; extra == 'tslime'
Requires-Dist: scipy ; extra == 'tslime'
Requires-Dist: requests ; extra == 'tslime'
Provides-Extra: tssaliency
Requires-Dist: pandas (<2.0.0) ; extra == 'tssaliency'
Requires-Dist: requests ; extra == 'tssaliency'
